{"success":"1","uniqueid":"222ec049-cecc-4343-897a-528add0c5a66","result":{"sentences":[{"sentenceID":0,"sentenceBoundingBox":{"top":"130","bottom":"341","right":"5141","left":"154"},"words":[{"boundingBox":{"top":"168","bottom":"288","right":"912","left":"154"},"word":"••000"},{"boundingBox":{"top":"139","bottom":"341","right":"1646","left":"989"},"word":"AT&T"},{"boundingBox":{"top":"134","bottom":"336","right":"2246","left":"1872"},"word":"LTE"},{"boundingBox":{"top":"134","bottom":"341","right":"5141","left":"4421"},"word":"19:57"}],"sentence":"••000 AT&T LTE 19:57 "},{"sentenceID":1,"sentenceBoundingBox":{"top":"504","bottom":"710","right":"5846","left":"3576"},"words":[{"boundingBox":{"top":"509","bottom":"701","right":"3715","left":"3576"},"word":"i"},{"boundingBox":{"top":"504","bottom":"710","right":"5846","left":"3859"},"word":"fortbendisd.com"}],"sentence":"i fortbendisd.com "},{"sentenceID":2,"sentenceBoundingBox":{"top":"869","bottom":"1138","right":"5136","left":"682"},"words":[{"boundingBox":{"top":"902","bottom":"1133","right":"840","left":"682"},"word":"2"},{"boundingBox":{"top":"907","bottom":"1138","right":"2390","left":"1325"},"word":"bottles"},{"boundingBox":{"top":"907","bottom":"1138","right":"2822","left":"2515"},"word":"of"},{"boundingBox":{"top":"907","bottom":"1138","right":"3691","left":"2938"},"word":"hand"},{"boundingBox":{"top":"902","bottom":"1138","right":"5136","left":"3821"},"word":"sanitizer"}],"sentence":"2 bottles of hand sanitizer "},{"sentenceID":3,"sentenceBoundingBox":{"top":"1325","bottom":"1680","right":"5362","left":"696"},"words":[{"boundingBox":{"top":"1354","bottom":"1608","right":"840","left":"696"},"word":"1"},{"boundingBox":{"top":"1378","bottom":"1613","right":"1766","left":"1315"},"word":"set"},{"boundingBox":{"top":"1325","bottom":"1680","right":"5362","left":"1886"},"word":"ear-buds/headphones"}],"sentence":"1 set ear-buds/headphones "},{"sentenceID":4,"sentenceBoundingBox":{"top":"1810","bottom":"2160","right":"5117","left":"1325"},"words":[{"boundingBox":{"top":"1814","bottom":"2160","right":"2914","left":"1325"},"word":"(preferred"},{"boundingBox":{"top":"1858","bottom":"2093","right":"3562","left":"3053"},"word":"not"},{"boundingBox":{"top":"1810","bottom":"2160","right":"5117","left":"3686"},"word":"required)"}],"sentence":"(preferred not required) "},{"sentenceID":5,"sentenceBoundingBox":{"top":"120","bottom":"346","right":"9322","left":"7454"},"words":[{"boundingBox":{"top":"130","bottom":"336","right":"7670","left":"7454"},"word":"0"},{"boundingBox":{"top":"120","bottom":"346","right":"9322","left":"8141"},"word":"43%x'"}],"sentence":"0 43%x' "},{"sentenceID":6,"sentenceBoundingBox":{"top":"2779","bottom":"3106","right":"3634","left":"715"},"words":[{"boundingBox":{"top":"2784","bottom":"3106","right":"1843","left":"715"},"word":"First"},{"boundingBox":{"top":"2779","bottom":"3106","right":"3634","left":"2006"},"word":"Grade"}],"sentence":"First Grade "},{"sentenceID":7,"sentenceBoundingBox":{"top":"3331","bottom":"3672","right":"4363","left":"682"},"words":[{"boundingBox":{"top":"3346","bottom":"3600","right":"1051","left":"682"},"word":"24"},{"boundingBox":{"top":"3346","bottom":"3600","right":"1670","left":"1310"},"word":"#2"},{"boundingBox":{"top":"3331","bottom":"3605","right":"3173","left":"1795"},"word":"standard"},{"boundingBox":{"top":"3331","bottom":"3672","right":"4363","left":"3307"},"word":"pencils"}],"sentence":"24 #2 standard pencils "},{"sentenceID":8,"sentenceBoundingBox":{"top":"3802","bottom":"4152","right":"4656","left":"682"},"words":[{"boundingBox":{"top":"3826","bottom":"4080","right":"840","left":"682"},"word":"2"},{"boundingBox":{"top":"3806","bottom":"4085","right":"2213","left":"1330"},"word":"boxes"},{"boundingBox":{"top":"3806","bottom":"4085","right":"2645","left":"2338"},"word":"of"},{"boundingBox":{"top":"3893","bottom":"4152","right":"3936","left":"2746"},"word":"crayons"},{"boundingBox":{"top":"3802","bottom":"4147","right":"4656","left":"4070"},"word":"(24)"}],"sentence":"2 boxes of crayons (24) "},{"sentenceID":9,"sentenceBoundingBox":{"top":"4272","bottom":"4632","right":"7882","left":"696"},"words":[{"boundingBox":{"top":"4306","bottom":"4560","right":"840","left":"696"},"word":"1"},{"boundingBox":{"top":"4286","bottom":"4565","right":"1862","left":"1315"},"word":"box"},{"boundingBox":{"top":"4286","bottom":"4632","right":"3120","left":"1973"},"word":"Crayola"},{"boundingBox":{"top":"4286","bottom":"4565","right":"4517","left":"3259"},"word":"markers"},{"boundingBox":{"top":"4272","bottom":"4627","right":"7882","left":"4642"},"word":"(standard/washable)"}],"sentence":"1 box Crayola markers (standard/washable) "},{"sentenceID":10,"sentenceBoundingBox":{"top":"4766","bottom":"5112","right":"5621","left":"696"},"words":[{"boundingBox":{"top":"4786","bottom":"5040","right":"840","left":"696"},"word":"1"},{"boundingBox":{"top":"4766","bottom":"5040","right":"1877","left":"1330"},"word":"box"},{"boundingBox":{"top":"4766","bottom":"5040","right":"2299","left":"1982"},"word":"of"},{"boundingBox":{"top":"4848","bottom":"5107","right":"3067","left":"2410"},"word":"map"},{"boundingBox":{"top":"4766","bottom":"5112","right":"4445","left":"3192"},"word":"coloring"},{"boundingBox":{"top":"4766","bottom":"5107","right":"5621","left":"4574"},"word":"pencils"}],"sentence":"1 box of map coloring pencils "},{"sentenceID":11,"sentenceBoundingBox":{"top":"5256","bottom":"5597","right":"4018","left":"696"},"words":[{"boundingBox":{"top":"5270","bottom":"5525","right":"840","left":"696"},"word":"1"},{"boundingBox":{"top":"5256","bottom":"5597","right":"2309","left":"1330"},"word":"plastic"},{"boundingBox":{"top":"5256","bottom":"5597","right":"3336","left":"2443"},"word":"pencil"},{"boundingBox":{"top":"5256","bottom":"5530","right":"4018","left":"3475"},"word":"box"}],"sentence":"1 plastic pencil box "},{"sentenceID":12,"sentenceBoundingBox":{"top":"5731","bottom":"6077","right":"5702","left":"696"},"words":[{"boundingBox":{"top":"5750","bottom":"6005","right":"840","left":"696"},"word":"1"},{"boundingBox":{"top":"5731","bottom":"6077","right":"2222","left":"1330"},"word":"pencil"},{"boundingBox":{"top":"5731","bottom":"6077","right":"3950","left":"2347"},"word":"sharpener"},{"boundingBox":{"top":"5731","bottom":"6010","right":"4723","left":"4056"},"word":"with"},{"boundingBox":{"top":"5818","bottom":"6010","right":"5702","left":"4848"},"word":"cover"}],"sentence":"1 pencil sharpener with cover "},{"sentenceID":13,"sentenceBoundingBox":{"top":"6211","bottom":"6557","right":"5942","left":"682"},"words":[{"boundingBox":{"top":"6230","bottom":"6485","right":"840","left":"682"},"word":"2"},{"boundingBox":{"top":"6211","bottom":"6490","right":"2390","left":"1330"},"word":"bottles"},{"boundingBox":{"top":"6211","bottom":"6490","right":"2832","left":"2515"},"word":"of"},{"boundingBox":{"top":"6211","bottom":"6490","right":"4070","left":"2947"},"word":"Elmer's"},{"boundingBox":{"top":"6211","bottom":"6490","right":"5165","left":"4186"},"word":"school"},{"boundingBox":{"top":"6211","bottom":"6557","right":"5942","left":"5290"},"word":"glue"}],"sentence":"2 bottles of Elmer's school glue "},{"sentenceID":14,"sentenceBoundingBox":{"top":"6691","bottom":"7037","right":"3797","left":"682"},"words":[{"boundingBox":{"top":"6710","bottom":"6965","right":"845","left":"682"},"word":"6"},{"boundingBox":{"top":"6691","bottom":"7037","right":"2078","left":"1330"},"word":"large"},{"boundingBox":{"top":"6691","bottom":"7037","right":"2837","left":"2189"},"word":"glue"},{"boundingBox":{"top":"6691","bottom":"6965","right":"3797","left":"2952"},"word":"sticks"}],"sentence":"6 large glue sticks "},{"sentenceID":15,"sentenceBoundingBox":{"top":"7171","bottom":"7512","right":"4104","left":"682"},"words":[{"boundingBox":{"top":"7190","bottom":"7440","right":"840","left":"682"},"word":"2"},{"boundingBox":{"top":"7171","bottom":"7512","right":"1973","left":"1330"},"word":"pink"},{"boundingBox":{"top":"7171","bottom":"7512","right":"2856","left":"2098"},"word":"pearl"},{"boundingBox":{"top":"7253","bottom":"7445","right":"4104","left":"2986"},"word":"erasers"}],"sentence":"2 pink pearl erasers "},{"sentenceID":16,"sentenceBoundingBox":{"top":"7651","bottom":"7925","right":"5813","left":"696"},"words":[{"boundingBox":{"top":"7670","bottom":"7920","right":"840","left":"696"},"word":"1"},{"boundingBox":{"top":"7651","bottom":"7920","right":"1838","left":"1334"},"word":"12\""},{"boundingBox":{"top":"7651","bottom":"7925","right":"2702","left":"1978"},"word":"ruler"},{"boundingBox":{"top":"7651","bottom":"7925","right":"3984","left":"2827"},"word":"marked"},{"boundingBox":{"top":"7666","bottom":"7925","right":"4464","left":"4123"},"word":"in."},{"boundingBox":{"top":"7651","bottom":"7925","right":"5155","left":"4603"},"word":"and"},{"boundingBox":{"top":"7733","bottom":"7925","right":"5813","left":"5280"},"word":"cm."}],"sentence":"1 12\" ruler marked in. and cm. "},{"sentenceID":17,"sentenceBoundingBox":{"top":"8131","bottom":"8472","right":"5669","left":"696"},"words":[{"boundingBox":{"top":"8150","bottom":"8400","right":"840","left":"696"},"word":"1"},{"boundingBox":{"top":"8146","bottom":"8472","right":"1910","left":"1330"},"word":"pair"},{"boundingBox":{"top":"8131","bottom":"8405","right":"2338","left":"2026"},"word":"of"},{"boundingBox":{"top":"8131","bottom":"8405","right":"3346","left":"2453"},"word":"Fiskar"},{"boundingBox":{"top":"8131","bottom":"8472","right":"4382","left":"3442"},"word":"safety"},{"boundingBox":{"top":"8146","bottom":"8405","right":"5669","left":"4488"},"word":"scissors"}],"sentence":"1 pair of Fiskar safety scissors "},{"sentenceID":18,"sentenceBoundingBox":{"top":"8616","bottom":"8962","right":"8035","left":"682"},"words":[{"boundingBox":{"top":"8635","bottom":"8890","right":"845","left":"682"},"word":"6"},{"boundingBox":{"top":"8616","bottom":"8942","right":"3043","left":"1315"},"word":"notebooks,"},{"boundingBox":{"top":"8635","bottom":"8942","right":"3989","left":"3173"},"word":"8x10,"},{"boundingBox":{"top":"8616","bottom":"8890","right":"4987","left":"4114"},"word":"white"},{"boundingBox":{"top":"8630","bottom":"8957","right":"6322","left":"5122"},"word":"primary"},{"boundingBox":{"top":"8698","bottom":"8962","right":"7416","left":"6451"},"word":"paper,"},{"boundingBox":{"top":"8616","bottom":"8894","right":"8035","left":"7555"},"word":"red"}],"sentence":"6 notebooks, 8x10, white primary paper, red "},{"sentenceID":19,"sentenceBoundingBox":{"top":"9096","bottom":"9422","right":"4483","left":"1315"},"words":[{"boundingBox":{"top":"9096","bottom":"9422","right":"2678","left":"1315"},"word":"baseline,"},{"boundingBox":{"top":"9096","bottom":"9370","right":"3542","left":"2803"},"word":"wide"},{"boundingBox":{"top":"9096","bottom":"9370","right":"4483","left":"3571"},"word":"-ruled"}],"sentence":"baseline, wide -ruled "},{"sentenceID":20,"sentenceBoundingBox":{"top":"9571","bottom":"9912","right":"9043","left":"682"},"words":[{"boundingBox":{"top":"9586","bottom":"9845","right":"840","left":"682"},"word":"3"},{"boundingBox":{"top":"9571","bottom":"9845","right":"2002","left":"1315"},"word":"hard"},{"boundingBox":{"top":"9653","bottom":"9845","right":"2986","left":"2131"},"word":"cover"},{"boundingBox":{"top":"9581","bottom":"9912","right":"5016","left":"3096"},"word":"composition"},{"boundingBox":{"top":"9571","bottom":"9898","right":"6883","left":"5160"},"word":"notebooks,"},{"boundingBox":{"top":"9581","bottom":"9912","right":"8227","left":"7022"},"word":"primary"},{"boundingBox":{"top":"9571","bottom":"9912","right":"9043","left":"8338"},"word":"style"}],"sentence":"3 hard cover composition notebooks, primary style "},{"sentenceID":21,"sentenceBoundingBox":{"top":"10056","bottom":"10397","right":"7656","left":"682"},"words":[{"boundingBox":{"top":"10075","bottom":"10325","right":"840","left":"682"},"word":"2"},{"boundingBox":{"top":"10056","bottom":"10397","right":"2731","left":"1315"},"word":"packages"},{"boundingBox":{"top":"10056","bottom":"10330","right":"3163","left":"2851"},"word":"of"},{"boundingBox":{"top":"10056","bottom":"10330","right":"4766","left":"3274"},"word":"notebook"},{"boundingBox":{"top":"10138","bottom":"10397","right":"5856","left":"4891"},"word":"paper,"},{"boundingBox":{"top":"10056","bottom":"10330","right":"6725","left":"5981"},"word":"wide"},{"boundingBox":{"top":"10056","bottom":"10330","right":"7656","left":"6758"},"word":"-ruled"}],"sentence":"2 packages of notebook paper, wide -ruled "},{"sentenceID":22,"sentenceBoundingBox":{"top":"10536","bottom":"10877","right":"6096","left":"696"},"words":[{"boundingBox":{"top":"10555","bottom":"10805","right":"840","left":"696"},"word":"1"},{"boundingBox":{"top":"10536","bottom":"10877","right":"2578","left":"1315"},"word":"package"},{"boundingBox":{"top":"10536","bottom":"10810","right":"3010","left":"2698"},"word":"of"},{"boundingBox":{"top":"10550","bottom":"10810","right":"5059","left":"3110"},"word":"construction"},{"boundingBox":{"top":"10618","bottom":"10877","right":"6096","left":"5198"},"word":"paper"}],"sentence":"1 package of construction paper "},{"sentenceID":23,"sentenceBoundingBox":{"top":"11016","bottom":"11357","right":"5966","left":"696"},"words":[{"boundingBox":{"top":"11030","bottom":"11285","right":"840","left":"696"},"word":"1"},{"boundingBox":{"top":"11016","bottom":"11357","right":"2078","left":"1330"},"word":"large"},{"boundingBox":{"top":"11030","bottom":"11290","right":"3696","left":"2198"},"word":"container"},{"boundingBox":{"top":"11016","bottom":"11290","right":"4118","left":"3811"},"word":"of"},{"boundingBox":{"top":"11016","bottom":"11357","right":"4963","left":"4229"},"word":"baby"},{"boundingBox":{"top":"11026","bottom":"11357","right":"5966","left":"5069"},"word":"wipes"}],"sentence":"1 large container of baby wipes "},{"sentenceID":24,"sentenceBoundingBox":{"top":"11496","bottom":"11842","right":"4939","left":"1325"},"words":[{"boundingBox":{"top":"11496","bottom":"11842","right":"1819","left":"1325"},"word":"(no"},{"boundingBox":{"top":"11582","bottom":"11842","right":"3048","left":"1949"},"word":"pop-up"},{"boundingBox":{"top":"11496","bottom":"11842","right":"4939","left":"3173"},"word":"dispensers)"}],"sentence":"(no pop-up dispensers) "},{"sentenceID":25,"sentenceBoundingBox":{"top":"11981","bottom":"12322","right":"5318","left":"682"},"words":[{"boundingBox":{"top":"12000","bottom":"12254","right":"845","left":"682"},"word":"6"},{"boundingBox":{"top":"11981","bottom":"12322","right":"2376","left":"1330"},"word":"pocket"},{"boundingBox":{"top":"11981","bottom":"12254","right":"3552","left":"2482"},"word":"folders"},{"boundingBox":{"top":"11981","bottom":"12254","right":"4339","left":"3672"},"word":"with"},{"boundingBox":{"top":"11981","bottom":"12254","right":"5318","left":"4478"},"word":"brads"}],"sentence":"6 pocket folders with brads "},{"sentenceID":26,"sentenceBoundingBox":{"top":"12456","bottom":"12802","right":"5400","left":"696"},"words":[{"boundingBox":{"top":"12480","bottom":"12730","right":"840","left":"696"},"word":"1"},{"boundingBox":{"top":"12461","bottom":"12734","right":"1872","left":"1330"},"word":"box"},{"boundingBox":{"top":"12461","bottom":"12734","right":"2299","left":"1982"},"word":"of"},{"boundingBox":{"top":"12461","bottom":"12802","right":"3307","left":"2390"},"word":"Ziploc"},{"boundingBox":{"top":"12461","bottom":"12802","right":"4123","left":"3432"},"word":"bags"},{"boundingBox":{"top":"12456","bottom":"12802","right":"5400","left":"4253"},"word":"(gallon)"}],"sentence":"1 box of Ziploc bags (gallon) "},{"sentenceID":27,"sentenceBoundingBox":{"top":"12926","bottom":"13277","right":"5304","left":"696"},"words":[{"boundingBox":{"top":"12950","bottom":"13205","right":"840","left":"696"},"word":"1"},{"boundingBox":{"top":"12931","bottom":"13210","right":"1872","left":"1330"},"word":"box"},{"boundingBox":{"top":"12931","bottom":"13210","right":"2299","left":"1982"},"word":"of"},{"boundingBox":{"top":"12931","bottom":"13277","right":"3307","left":"2390"},"word":"Ziploc"},{"boundingBox":{"top":"12931","bottom":"13277","right":"4123","left":"3432"},"word":"bags"},{"boundingBox":{"top":"12926","bottom":"13277","right":"5304","left":"4253"},"word":"(quart)"}],"sentence":"1 box of Ziploc bags (quart) "},{"sentenceID":28,"sentenceBoundingBox":{"top":"13416","bottom":"13762","right":"5448","left":"682"},"words":[{"boundingBox":{"top":"13435","bottom":"13690","right":"840","left":"682"},"word":"2"},{"boundingBox":{"top":"13421","bottom":"13762","right":"2078","left":"1330"},"word":"large"},{"boundingBox":{"top":"13421","bottom":"13694","right":"3091","left":"2208"},"word":"boxes"},{"boundingBox":{"top":"13416","bottom":"13694","right":"3528","left":"3216"},"word":"of"},{"boundingBox":{"top":"13416","bottom":"13694","right":"4421","left":"3614"},"word":"facial"},{"boundingBox":{"top":"13430","bottom":"13694","right":"5448","left":"4536"},"word":"tissue"}],"sentence":"2 large boxes of facial tissue "},{"sentenceID":29,"sentenceBoundingBox":{"top":"13896","bottom":"14174","right":"5136","left":"682"},"words":[{"boundingBox":{"top":"13915","bottom":"14170","right":"840","left":"682"},"word":"2"},{"boundingBox":{"top":"13901","bottom":"14174","right":"2390","left":"1330"},"word":"bottles"},{"boundingBox":{"top":"13896","bottom":"14174","right":"2832","left":"2515"},"word":"of"},{"boundingBox":{"top":"13901","bottom":"14174","right":"3691","left":"2942"},"word":"hand"},{"boundingBox":{"top":"13910","bottom":"14174","right":"5136","left":"3821"},"word":"sanitizer"}],"sentence":"2 bottles of hand sanitizer "},{"sentenceID":30,"sentenceBoundingBox":{"top":"14366","bottom":"14722","right":"9130","left":"696"},"words":[{"boundingBox":{"top":"14395","bottom":"14650","right":"840","left":"696"},"word":"1"},{"boundingBox":{"top":"14419","bottom":"14654","right":"1766","left":"1315"},"word":"set"},{"boundingBox":{"top":"14366","bottom":"14722","right":"5218","left":"1886"},"word":"ear-buds/headphone"},{"boundingBox":{"top":"14376","bottom":"14722","right":"6926","left":"5342"},"word":"(preferred"},{"boundingBox":{"top":"14419","bottom":"14654","right":"7574","left":"7070"},"word":"not"},{"boundingBox":{"top":"14376","bottom":"14722","right":"9130","left":"7690"},"word":"required)"}],"sentence":"1 set ear-buds/headphone (preferred not required) "}]}}